persidict/__init__.py
persidict/_version_info.py
persidict/basic_s3_dict.py
persidict/cached_appendonly_dict.py
persidict/cached_mutable_dict.py
persidict/empty_dict.py
persidict/file_dir_dict.py
persidict/jokers_and_status_flags.py
persidict/local_dict.py
persidict/overlapping_multi_dict.py
persidict/persi_dict.py
persidict/py.typed
persidict/s3_dict_file_dir_cached.py
persidict/safe_chars.py
persidict/safe_str_tuple.py
persidict/safe_str_tuple_signing.py
persidict/write_once_dict.py
persidict-0.110.4.dist-info/METADATA
persidict-0.110.4.dist-info/WHEEL
persidict-0.110.4.dist-info/licenses/LICENSE
persidict-0.110.4.dist-info/RECORD
