Metadata-Version: 2.4
Name: persidict
Version: 0.110.4
Summary: Simple persistent key-value store for Python. Values are stored as files on a disk or as S3 objects on AWS cloud.
Project-URL: Home, https://github.com/pythagoras-dev/persidict
Project-URL: Docs, https://persidict.readthedocs.io/
Author-email: "Vlad (Volodymyr) Pavlov" <vlpavlov@ieee.org>
License: MIT
License-File: LICENSE
Keywords: dicts,distributed,parallel,persistence
Classifier: Development Status :: 4 - Beta
Classifier: Intended Audience :: Developers
Classifier: Intended Audience :: Science/Research
Classifier: License :: OSI Approved :: MIT License
Classifier: Operating System :: OS Independent
Classifier: Programming Language :: Python
Classifier: Programming Language :: Python :: 3
Classifier: Programming Language :: Python :: 3.11
Classifier: Programming Language :: Python :: 3.12
Classifier: Programming Language :: Python :: 3.13
Classifier: Programming Language :: Python :: 3.14
Classifier: Topic :: Software Development :: Libraries
Classifier: Topic :: Software Development :: Libraries :: Python Modules
Classifier: Typing :: Typed
Requires-Python: >=3.11
Requires-Dist: boto3
Requires-Dist: deepdiff
Requires-Dist: joblib
Requires-Dist: jsonpickle
Requires-Dist: lz4
Requires-Dist: mixinforge
Requires-Dist: pandas
Requires-Dist: pytest
Requires-Dist: uv
Provides-Extra: aws
Requires-Dist: boto3; extra == 'aws'
Provides-Extra: dev
Requires-Dist: boto3; extra == 'dev'
Requires-Dist: coverage; extra == 'dev'
Requires-Dist: moto; extra == 'dev'
Requires-Dist: mypy; extra == 'dev'
Requires-Dist: numpy; extra == 'dev'
Requires-Dist: pandas; extra == 'dev'
Requires-Dist: pydata-sphinx-theme; extra == 'dev'
Requires-Dist: pytest; extra == 'dev'
Requires-Dist: sphinx; extra == 'dev'
Provides-Extra: docs
Requires-Dist: furo; extra == 'docs'
Requires-Dist: pydata-sphinx-theme; extra == 'docs'
Requires-Dist: sphinx; extra == 'docs'
